hitherecli/__init__.py
hitherecli/__main__.py
hitherecli/hitherecli.py
hitherecli-0.1.dist-info/LICENCE
hitherecli-0.1.dist-info/METADATA
hitherecli-0.1.dist-info/WHEEL
hitherecli-0.1.dist-info/entry_points.txt
hitherecli-0.1.dist-info/top_level.txt
hitherecli-0.1.dist-info/RECORD
